pyfoot/__init__.py
pyfoot/__main__.py
pyfoot/constants.py
pyfoot/main.py
pyfoot/textinput.py
pyfoot/types.py
pyfoot/Examples/example.py
pyfoot/default_images/pyfoot_logo.png
pyfoot-0.1.3.dist-info/LICENSE
pyfoot-0.1.3.dist-info/METADATA
pyfoot-0.1.3.dist-info/WHEEL
pyfoot-0.1.3.dist-info/top_level.txt
pyfoot-0.1.3.dist-info/RECORD
