Metadata-Version: 2.1
Name: pyfoot
Version: 0.1.3
Summary: A simple simple and beginner friendly library for writing 2D games based on pygame and inspired by Greenfoot
Home-page: https://github.com/Threated/pyfoot
Author: Jan Skiba
Author-email: jan2001.07@gmail.com
License: GNU 3
Platform: UNKNOWN
Requires-Python: >=3.6
Requires-Dist: pygame
